LICENSE
MANIFEST.in
README.rst
makemigrations.py
migrate.py
setup.cfg
setup.py
django_fakejira_final_app_1.egg-info/PKG-INFO
django_fakejira_final_app_1.egg-info/SOURCES.txt
django_fakejira_final_app_1.egg-info/dependency_links.txt
django_fakejira_final_app_1.egg-info/requires.txt
django_fakejira_final_app_1.egg-info/top_level.txt
fakejira1/__init__.py
fakejira1/admin.py
fakejira1/apps.py
fakejira1/forms.py
fakejira1/models.py
fakejira1/schema.py
fakejira1/tests.py
fakejira1/urls.py
fakejira1/views.py
fakejira1/__pycache__/__init__.cpython-39.pyc
fakejira1/__pycache__/admin.cpython-39.pyc
fakejira1/__pycache__/forms.cpython-39.pyc
fakejira1/__pycache__/models.cpython-39.pyc
fakejira1/__pycache__/urls.cpython-39.pyc
fakejira1/__pycache__/views.cpython-39.pyc
fakejira1/migrations/0001_initial.py
fakejira1/migrations/__init__.py
fakejira1/migrations/__pycache__/0001_initial.cpython-39.pyc
fakejira1/migrations/__pycache__/__init__.cpython-39.pyc
fakejira1/static/login.css
fakejira1/static/main.css
fakejira1/static/js/main.js
fakejira1/templates/base.html
fakejira1/templates/manage_users.html
fakejira1/templates/selected_shipping.html
fakejira1/templates/shipping_create.html
fakejira1/templates/shippings.html
fakejira1/templates/filter/shippings-results.html
fakejira1/templates/filter/users-results.html
fakejira1/templates/user/login.html